pipelined_adder/main.v
//4 bit ripple carry adder in pipeline model


module pipe_rca4 (Cout, Sum, A, B, Cin, Clk);
  
  input [3:0] A,B;
  input Clk, Cin;
  output  [3:0] Sum;
  output   Cout;
  
  reg L1A1,L1A2,L1A3,L1B1,L1B2,L1B3,L1CI,L2A2,L2A3,L2B2,L2B3,L2CI,L3A3,L3B3,L3CI,L4CI,L1S0,L1S1,L2S0,L2S1,L2S2,L3S0,L3S1,L3S2,L3S3,L4S0,L4S1,L4S2,L4S3,L4S4;

  assign Sum[0]=L4S0;
 assign Sum[1]=L4S1;
 assign Sum[2]=L4S2;
 assign Sum[3]=L4S3;

 assign Cout= L4CI;

  always@(posedge Clk)
  begin
	  {L1CI,L1S0}<=A[0]+B[0]+Cin;
	  {L1A1,L1B1,L1A2,L1B2,L1A3,L1B3}<={A[1],B[1],A[2],B[2],A[3],B[3]};
  end  

  always@(posedge Clk)
  begin
	  {L2CI,L2S1}<=L1A1+L1B1+L1CI;
	  {L2S0,L2A2,L2B2,L2A3,L2B3}<={L1S0,L1A2,L1B2,L1A3,L1B3};


  end

  always@(posedge Clk)
  begin
	  {L3CI,L3S2}<=L2A2+L2B2+L2CI;
	  {L3S0,L3S1,L3A3,L3B3}<={L2S0,L2S1,L2A3,L2B3};
  end

  always@(posedge Clk)
  begin
	  {L4CI,L4S3} <= L3A3+L3B3+L3CI;
	  {L4S0,L4S1,L4S2}<={L3S0,L3S1,L3S2};
  end

endmodule

pipelined_adder/test.v
`include "main.v"

module pipe_rca4_test;
    reg [3:0] A, B, A_prev, B_prev;
    reg Cin, Cin_prev, Clk;
    wire [3:0] Sum;
    wire Cout;

    parameter STDIN = 32'h8000_0000;
    integer testid=0;
    integer ret;

    pipe_rca4 DUT (Cout, Sum, A, B, Cin, Clk);

    initial begin
        Clk = 1'b0;
        #500 $finish;
    end

    always #5 Clk = ~Clk;

    initial begin
           
     #2  A = 7; B = 5; Cin = 0;
                       #10 A_prev = A; B_prev = B; Cin_prev = Cin; A = 0; B = 0; Cin = 0;
                       #30;testid=1;
                               #2  A = 7; B = 5; Cin = 1;
                       #10 A_prev = A; B_prev = B; Cin_prev = Cin; A = 0; B = 0; Cin = 0;
                       #30;testid=2;
                            #2  A = 10; B = 6; Cin = 0;
                       #10 A_prev = A; B_prev = B; Cin_prev = Cin; A = 0; B = 0; Cin = 0;
                       #30;testid=3;
                       #2  A = 4; B = 10; Cin = 1;
                       #10 A_prev = A; B_prev = B; Cin_prev = Cin; A = 0; B = 0; Cin = 0;
                       #30;testid=4;
                            #2  A = 0; B = 6; Cin = 1;
                       #10 A_prev = A; B_prev = B; Cin_prev = Cin; A = 0; B = 0; Cin = 0;
                       #30;testid=5;
                             #2  A = 0; B = 0; Cin = 0;
                       #10 A_prev = A; B_prev = B; Cin_prev = Cin; A = 2; B = 2; Cin = 2;
                       #30;testid=6;
       #2  A = 0; B = 0; Cin = 1;
                       #10 A_prev = A; B_prev = B; Cin_prev = Cin; A = 0; B = 0; Cin = 0;
                       #30;
                      #2  A = 3; B = 0; Cin = 0;
                       #10 A_prev = A; B_prev = B; Cin_prev = Cin; A = 0; B = 0; Cin = 0;#1;
	       end      
           

		  initial begin
			  $dumpfile("d.vcd");
			  $dumpvars(2);
                   $monitor($time, "(A = %b and B = %b and Cin = %b) => (Sum = %b and  Cout = %b)", A_prev, B_prev, Cin_prev, Sum, Cout);
             #500 $finish;
  
       end
     
endmodule

pipelined_adder/d.vcd
$date
	Thu Sep 14 11:26:57 2023
$end
$version
	Icarus Verilog
$end
$timescale
	1s
$end
$scope module pipe_rca4_test $end
$var wire 4 ! Sum [3:0] $end
$var wire 1 " Cout $end
$var reg 4 # A [3:0] $end
$var reg 4 $ A_prev [3:0] $end
$var reg 4 % B [3:0] $end
$var reg 4 & B_prev [3:0] $end
$var reg 1 ' Cin $end
$var reg 1 ( Cin_prev $end
$var reg 1 ) Clk $end
$var integer 32 * testid [31:0] $end
$scope module DUT $end
$var wire 4 + A [3:0] $end
$var wire 4 , B [3:0] $end
$var wire 1 ' Cin $end
$var wire 1 ) Clk $end
$var wire 1 " Cout $end
$var wire 4 - Sum [3:0] $end
$var reg 1 . L1A1 $end
$var reg 1 / L1A2 $end
$var reg 1 0 L1A3 $end
$var reg 1 1 L1B1 $end
$var reg 1 2 L1B2 $end
$var reg 1 3 L1B3 $end
$var reg 1 4 L1CI $end
$var reg 1 5 L1S0 $end
$var reg 1 6 L2A2 $end
$var reg 1 7 L2A3 $end
$var reg 1 8 L2B2 $end
$var reg 1 9 L2B3 $end
$var reg 1 : L2CI $end
$var reg 1 ; L2S0 $end
$var reg 1 < L2S1 $end
$var reg 1 = L3A3 $end
$var reg 1 > L3B3 $end
$var reg 1 ? L3CI $end
$var reg 1 @ L3S0 $end
$var reg 1 A L3S1 $end
$var reg 1 B L3S2 $end
$var reg 1 C L4CI $end
$var reg 1 D L4S0 $end
$var reg 1 E L4S1 $end
$var reg 1 F L4S2 $end
$var reg 1 G L4S3 $end
$upscope $end
$upscope $end
$enddefinitions $end
#0
$dumpvars
xG
xF
xE
xD
xC
xB
xA
x@
x?
x>
x=
x<
x;
x:
x9
x8
x7
x6
x5
x4
x3
x2
x1
x0
x/
x.
bx -
bx ,
bx +
b0 *
0)
x(
x'
bx &
bx %
bx $
bx #
x"
bx !
$end
#2
0'
b101 %
b101 ,
b111 #
b111 +
#5
1.
01
1/
12
00
03
14
05
1)
#10
0)
#12
b0 %
b0 ,
b0 #
b0 +
0(
b101 &
b111 $
#15
0;
16
18
07
09
1:
0<
0.
0/
02
04
1)
#20
0)
#25
06
08
0:
0@
0A
0=
0>
1?
1B
1)
#30
0)
#35
0D
0E
1F
0"
0C
b1100 !
b1100 -
1G
0?
0B
1)
#40
0)
#42
b1 *
#44
1'
b101 %
b101 ,
b111 #
b111 +
#45
1.
1/
12
14
15
0F
b0 !
b0 -
0G
1)
#50
0)
#54
0'
b0 %
b0 ,
b0 #
b0 +
1(
#55
1;
16
18
1:
0.
0/
02
04
05
1)
#60
0)
#65
0;
06
08
0:
1@
1?
1B
1)
#70
0)
#75
1D
1F
b1101 !
b1101 -
1G
0@
0?
0B
1)
#80
0)
#84
b10 *
#85
0D
0F
b0 !
b0 -
0G
1)
#86
b110 %
b110 ,
b1010 #
b1010 +
#90
0)
#95
1.
11
12
10
1)
#96
b0 %
b0 ,
b0 #
b0 +
0(
b110 &
b1010 $
#100
0)
#105
0.
01
02
00
18
17
1:
1)
#110
0)
#115
1=
1?
08
07
0:
1)
#120
0)
#125
0=
0?
1"
1C
1)
#126
b11 *
#128
1'
b1010 %
b1010 ,
b100 #
b100 +
#130
0)
#135
0"
0C
11
1/
13
15
1)
#138
0'
b0 %
b0 ,
b0 #
b0 +
1(
b1010 &
b100 $
#140
0)
#145
01
0/
03
05
1;
16
19
1<
1)
#150
0)
#155
1@
1A
1>
1B
0;
06
09
0<
1)
#160
0)
#165
0@
0A
0>
0B
1D
1E
1F
b1111 !
b1111 -
1G
1)
#168
b100 *
#170
1'
b110 %
b110 ,
0)
#175
0D
0E
0F
b0 !
b0 -
0G
11
12
15
1)
#180
0)
0'
b0 %
b0 ,
b110 &
b0 $
#185
01
02
05
1;
18
1<
1)
#190
0)
#195
1@
1A
1B
0;
08
0<
1)
#200
0)
#205
0@
0A
0B
1D
1E
b111 !
b111 -
1F
1)
#210
0)
b101 *
#215
0D
0E
b0 !
b0 -
0F
1)
#220
0)
#222
b10 %
b10 ,
b10 #
b10 +
0(
b0 &
#225
1.
11
1)
#230
0)
#235
1:
1)
#240
0)
#245
1B
1)
#250
0)
#252
b110 *
#254
1'
b0 %
b0 ,
b0 #
b0 +
#255
b100 !
b100 -
1F
0.
01
15
1)
#260
0)
#264
0'
1(
#265
05
1;
0:
1)
#270
0)
#275
1@
0B
0;
1)
#280
0)
#285
0@
1D
b1 !
b1 -
0F
1)
#290
0)
#295
b0 !
b0 -
0D
1)
#296
b11 #
b11 +
#300
0)
#305
1.
15
1)
#306
b0 #
b0 +
0(
b11 $
#310
0)
#315
1;
1<
0.
05
1)
#320
0)
#325
0;
0<
1@
1A
1)
#330
0)
#335
1D
b11 !
b11 -
1E
0@
0A
1)
#340
0)
#345
0D
b0 !
b0 -
0E
1)
